TwoReversedList/TwoReversedList.py
TwoReversedList/__init__.py
TwoReversedList-1.1.40.dist-info/METADATA
TwoReversedList-1.1.40.dist-info/WHEEL
TwoReversedList-1.1.40.dist-info/top_level.txt
TwoReversedList-1.1.40.dist-info/RECORD
