Metadata-Version: 2.1
Name: TwoReversedList
Version: 1.1.40
Summary: A module to reverse lists
Home-page: UNKNOWN
Author: Sahand Pourjavad
Author-email: <sahndpourjavad@gmail.com>
License: UNKNOWN
Keywords: python,Lists
Platform: UNKNOWN
